setup.py
free_sample_api/__init__.py
free_sample_api/search.py
free_sample_api.egg-info/PKG-INFO
free_sample_api.egg-info/SOURCES.txt
free_sample_api.egg-info/dependency_links.txt
free_sample_api.egg-info/top_level.txt