Metadata-Version: 2.1
Name: free-sample-api
Version: 0.1.0
Summary: Free Sample API
Classifier: Intended Audience :: Developers
Classifier: Operating System :: POSIX :: Linux
Classifier: Programming Language :: Python :: 3.5
